{
  "description": "Servitium linguae integratum pro Typst",
  "extension.tinymist.command.tinymist.exportCurrentPdf": "Exportare apertum fasciculum ut PDF",
  "extension.tinymist.command.tinymist.pinMainToCurrent": "Pango fasciculum principale ad documentum apertum",
  "extension.tinymist.command.tinymist.unpinMain": "Solve fasciculum principale",
  "extension.tinymist.command.tinymist.showPdf": "Ostende PDF exportatum",
  "extension.tinymist.command.tinymist.copyAnsiHighlight": "Copia ut ANSI Code",
  "extension.tinymist.command.tinymist.showLog": "Tinymist: Ostende Log",
  "extension.tinymist.command.tinymist.restartServer": "Reincita servientem",
  "extension.tinymist.command.tinymist.clearCache": "Purgare omnes opes in cache",
  "extension.tinymist.command.tinymist.initTemplate": "Initialize novum Typst projectum ex forma",
  "extension.tinymist.command.tinymist.initTemplateInPlace": "Insere contentum formae in loco",
  "extension.tinymist.command.tinymist.showTemplateGallery": "Ostende formas Typst praesto (galeria) ad sumendam formam ad initializandum",
  "extension.tinymist.command.tinymist.createLocalPackage": "Crea fasciculum locale Typst",
  "extension.tinymist.command.tinymist.openLocalPackage": "Aperi fasciculum locale Typst",
  "extension.tinymist.command.tinymist.showSummary": "Ostende summarium documenti currentis",
  "extension.tinymist.command.tinymist.showSymbolView": "Ostende visum symboli",
  "extension.tinymist.command.tinymist.showFontView": "Ostende visum fontis",
  "extension.tinymist.command.tinymist.syncLabel": "Perlustra spatium laboris et collige omnes titulos iterum",
  "extension.tinymist.command.tinymist.browsingPreview": "Praevideo navigationis",
  "extension.tinymist.command.typst-preview.preview": "Typst Preview: Praevideo fasciculi aperti",
  "extension.tinymist.command.typst-preview.browser": "Typst Preview: Praevideo fasciculi aperti in navigatro",
  "extension.tinymist.command.typst-preview.preview-slide": "Typst Preview: Praevideo fasciculi aperti in modo diapositivae",
  "extension.tinymist.command.typst-preview.browser-slide": "Typst Preview: Praevideo fasciculi aperti in navigatro et modo diapositivae",
  "extension.tinymist.command.typst-preview.eject": "Typst Preview: Praevideo tabulam eicere",
  "extension.tinymist.command.typst-preview.sync": "Typst Preview: Synchroniza praevideo cum cursore currenti",
  "extension.tinymist.command.typst-preview.noteOutline": "Nota: Saltus ad locum fontis elementi schematis non bene operatur si corpus eius locum fontis non habet, exempli gratia\n```\n#let my-heading(h) = heading(h) // huc saliet\n#my-heading(\"Title\") // huc non saliet\n```.\nQuare, fortasse vis uti `my-heading[Title]` pro meliori experientia saltus schematis."
}