{
  "description": "Un servizio linguistico integrato per Typst",
  "extension.tinymist.command.tinymist.exportCurrentPdf": "Esporta il file aperto come PDF",
  "extension.tinymist.command.tinymist.pinMainToCurrent": "Fissa il file principale al documento aperto",
  "extension.tinymist.command.tinymist.unpinMain": "Sblocca il file principale",
  "extension.tinymist.command.tinymist.showPdf": "Mostra PDF esportato",
  "extension.tinymist.command.tinymist.copyAnsiHighlight": "Copia come codice ANSI",
  "extension.tinymist.command.tinymist.showLog": "Tinymist: Mostra registro",
  "extension.tinymist.command.tinymist.restartServer": "Riavvia server",
  "extension.tinymist.command.tinymist.clearCache": "Cancella tutte le risorse memorizzate nella cache",
  "extension.tinymist.command.tinymist.initTemplate": "Inizializza un nuovo progetto Typst basato su un modello",
  "extension.tinymist.command.tinymist.initTemplateInPlace": "Inserisci il contenuto della voce del modello sul posto",
  "extension.tinymist.command.tinymist.showTemplateGallery": "Mostra i modelli Typst disponibili (galleria) per scegliere un modello da inizializzare",
  "extension.tinymist.command.tinymist.createLocalPackage": "Crea pacchetto locale Typst",
  "extension.tinymist.command.tinymist.openLocalPackage": "Apri pacchetto locale Typst",
  "extension.tinymist.command.tinymist.showSummary": "Mostra il riepilogo del documento corrente",
  "extension.tinymist.command.tinymist.showSymbolView": "Mostra vista simboli",
  "extension.tinymist.command.tinymist.showFontView": "Mostra vista font",
  "extension.tinymist.command.tinymist.syncLabel": "Scansiona l'area di lavoro e raccogli di nuovo tutte le etichette",
  "extension.tinymist.command.tinymist.browsingPreview": "Anteprima di navigazione",
  "extension.tinymist.command.typst-preview.preview": "Typst Preview: Anteprima del file aperto",
  "extension.tinymist.command.typst-preview.browser": "Typst Preview: Anteprima del file aperto nel browser",
  "extension.tinymist.command.typst-preview.preview-slide": "Typst Preview: Anteprima del file aperto in modalità diapositiva",
  "extension.tinymist.command.typst-preview.browser-slide": "Typst Preview: Anteprima del file aperto nel browser e in modalità diapositiva",
  "extension.tinymist.command.typst-preview.eject": "Typst Preview: Espelli il pannello di anteprima",
  "extension.tinymist.command.typst-preview.sync": "Typst Preview: Sincronizza anteprima con il cursore corrente",
  "extension.tinymist.command.typst-preview.noteOutline": "Nota: Il salto alla posizione di origine dell'elemento della struttura non funziona bene se il suo corpo non ha una posizione di origine, ad esempio\n```\n#let my-heading(h) = heading(h) // salterà qui\n#my-heading(\"Title\") // non salterà qui\n```.\nPertanto, potresti voler usare `my-heading[Title]` invece per ottenere una migliore esperienza di salto alla struttura."
}